buildcatrust/__init__.py
buildcatrust/certstore_output.py
buildcatrust/certstore_parser.py
buildcatrust/cli.py
buildcatrust/der_x509.py
buildcatrust/enums.py
buildcatrust/nss_parser.py
buildcatrust/p11kit_output.py
buildcatrust/types.py
buildcatrust/x509_consts.py
buildcatrust/tests/__init__.py
buildcatrust/tests/helpers.py
buildcatrust/tests/test_certstore_output.py
buildcatrust/tests/test_certstore_parser.py
buildcatrust/tests/test_der_x509.py
buildcatrust/tests/test_main.py
buildcatrust/tests/test_nonhermetic.py
buildcatrust/tests/test_p11kit_output.py
buildcatrust/tests/test_parser.py
buildcatrust/tests/test_types.py
buildcatrust/tests/testdata/blocklist-certumec384.txt
buildcatrust/tests/testdata/blocklist-certumec384.txt.license
buildcatrust/tests/testdata/certdata-certumec384.txt
buildcatrust/tools/parse_axeman_csv.py
buildcatrust-0.4.0.dist-info/entry_points.txt
buildcatrust-0.4.0.dist-info/licenses/AUTHORS
buildcatrust-0.4.0.dist-info/licenses/LICENSES/CC-BY-4.0.txt
buildcatrust-0.4.0.dist-info/licenses/LICENSES/CC0-1.0.txt
buildcatrust-0.4.0.dist-info/licenses/LICENSES/MIT.txt
buildcatrust-0.4.0.dist-info/licenses/LICENSES/MPL-2.0.txt
buildcatrust-0.4.0.dist-info/WHEEL
buildcatrust-0.4.0.dist-info/METADATA
buildcatrust-0.4.0.dist-info/RECORD
