Metadata-Version: 2.4
Name: buildcatrust
Version: 0.4.0
Summary: Utilities for turning one trust store into another.
Author-email: Luke Granger-Brown <buildcatrust@lukegb.com>, Ryan Lahfa <ryan@lahfa.xyz>
Maintainer-email: Luke Granger-Brown <buildcatrust@lukegb.com>
Requires-Python: >=3.11
License-Expression: MIT
License-File: AUTHORS
License-File: LICENSES/CC-BY-4.0.txt
License-File: LICENSES/CC0-1.0.txt
License-File: LICENSES/MIT.txt
License-File: LICENSES/MPL-2.0.txt
Project-URL: Source, https://github.com/nix-community/buildcatrust
